survshap/__init__.py
survshap/explainer.py
survshap/model_explanations/__init__.py
survshap/model_explanations/object.py
survshap/model_explanations/plot.py
survshap/model_explanations/utils.py
survshap/predict_explanations/__init__.py
survshap/predict_explanations/object.py
survshap/predict_explanations/plot.py
survshap/predict_explanations/utils.py
survshap-0.4.1.dist-info/METADATA
survshap-0.4.1.dist-info/WHEEL
survshap-0.4.1.dist-info/licenses/LICENSE
survshap-0.4.1.dist-info/RECORD
