Metadata-Version: 2.1
Name: survshap
Version: 0.4.1
Summary: Implementation of the SurvSHAP(t) explanation method for time-dependent explainability of machine learning survival models
Project-URL: Homepage, https://github.com/MI2DataLab/survshap
Project-URL: Bug Tracker, https://github.com/MI2DataLab/survshap/issues
Author: Mikołaj Spytek, Hubert Baniecki, Przemysław Biecek
Author-email: Mateusz Krzyziński <krzyzinskimateusz23@gmail.com>
License-File: LICENSE
Classifier: License :: OSI Approved :: MIT License
Classifier: Operating System :: OS Independent
Classifier: Programming Language :: Python :: 3
Requires-Python: >=3.7
Requires-Dist: numpy>=1.20.3
Requires-Dist: pandas>=1.2.5
Requires-Dist: plotly>=5.1.0
Requires-Dist: scikit-survival>=0.17.2
Requires-Dist: scipy>=1.6.3
Requires-Dist: shap>0.41.0
Requires-Dist: statsmodels>=0.13.2
Requires-Dist: tqdm>=4.61.2
